soundit.py
soundit-0.4.dist-info/METADATA
soundit-0.4.dist-info/WHEEL
soundit-0.4.dist-info/licenses/LICENSE
soundit-0.4.dist-info/RECORD
