Metadata-Version: 2.1
Name: soundit
Version: 0.4
Summary: Make audio
Project-URL: Homepage, https://pypi.org/project/soundit/
Project-URL: Repository, https://github.com/GeeTransit/soundit
Author-email: George Zhang <geetransit@gmail.com>
License: MIT
License-File: LICENSE
Classifier: Development Status :: 3 - Alpha
Classifier: License :: OSI Approved :: MIT License
Classifier: Operating System :: OS Independent
Classifier: Programming Language :: Python :: 3
Classifier: Programming Language :: Python :: 3.9
Classifier: Topic :: Multimedia :: Sound/Audio
Requires-Python: >=3.7
Requires-Dist: typing-extensions>=4.0.0; python_version < '3.10'
Provides-Extra: discord
Requires-Dist: discord-py>=1.7.0; extra == 'discord'
Provides-Extra: sounddevice
Requires-Dist: sounddevice>=0.4.0; extra == 'sounddevice'
